INSTALL.rst
LICENSE
MANIFEST.in
README.rst
VERSION
requirements.txt
setup.py
tasks.py
src/out.jpg
src/encrypter_pictures/__init__.py
src/encrypter_pictures/__main__.py
src/encrypter_pictures/__meta__.py
src/encrypter_pictures/cript.py
src/encrypter_pictures/encrypt.png
src/encrypter_pictures/exit24.png
src/encrypter_pictures/expand.png
src/encrypter_pictures/fraz.jpg
src/encrypter_pictures/gui.py
src/encrypter_pictures/info.png
src/encrypter_pictures/jpg.jpg
src/encrypter_pictures/open.png
src/encrypter_pictures/out.jpg
src/encrypter_pictures/print.png
src/encrypter_pictures/pyqt.png
src/encrypter_pictures/zoom.png
src/encrypter_pictures/zoom_in.png
src/encrypter_pictures/zoom_out.png
src/encrypter_pictures.egg-info/PKG-INFO
src/encrypter_pictures.egg-info/SOURCES.txt
src/encrypter_pictures.egg-info/dependency_links.txt
src/encrypter_pictures.egg-info/entry_points.txt
src/encrypter_pictures.egg-info/not-zip-safe
src/encrypter_pictures.egg-info/requires.txt
src/encrypter_pictures.egg-info/top_level.txt
src/encrypter_pictures/tests/__init__.py
src/encrypter_pictures/tests/test_encrypter_pictures.py