Metadata-Version: 1.1
Name: encrypter-pictures
Version: 1.0.2
Summary: System wich cat a image and crip and decript it with rsa.
Home-page: https://github.com/TiagoAssuncao/encrypter_pictures
Author: Tiago Assuncao
Author-email: tiago@sof2u.com
License: UNKNOWN
Platform: any
Classifier: Development Status :: 3 - Alpha
Classifier: Intended Audience :: Developers
Classifier: License :: OSI Approved :: GNU General Public License (GPL)
Classifier: Operating System :: POSIX
Classifier: Programming Language :: Python
Classifier: Topic :: Software Development :: Libraries
